waka_jlab/__init__.py
waka_jlab/_version.py
waka_jlab/handlers.py
waka_jlab-0.1.2.data/data/etc/jupyter/jupyter_server_config.d/waka_jlab.json
waka_jlab-0.1.2.data/data/share/jupyter/labextensions/waka-jlab/package.json
waka_jlab-0.1.2.data/data/share/jupyter/labextensions/waka-jlab/static/183.eaa9cbf387fff8b97a91.js
waka_jlab-0.1.2.data/data/share/jupyter/labextensions/waka-jlab/static/747.98ae87ea71d310834ae0.js
waka_jlab-0.1.2.data/data/share/jupyter/labextensions/waka-jlab/static/remoteEntry.209c4f54771165fc0a20.js
waka_jlab-0.1.2.data/data/share/jupyter/labextensions/waka-jlab/static/style.js
waka_jlab-0.1.2.data/data/share/jupyter/labextensions/waka-jlab/static/third-party-licenses.json
waka_jlab-0.1.2.data/data/share/jupyter/labextensions/waka-jlab/install.json
waka_jlab-0.1.2.dist-info/METADATA
waka_jlab-0.1.2.dist-info/WHEEL
waka_jlab-0.1.2.dist-info/licenses/LICENSE
waka_jlab-0.1.2.dist-info/RECORD
