Metadata-Version: 2.1
Name: waka_jlab
Version: 0.1.2
Summary: A JupyterLab WakaTime extension.
Project-URL: Homepage, https://github.com/AllanChain/waka-jlab
Project-URL: Bug Tracker, https://github.com/AllanChain/waka-jlab/issues
Project-URL: Repository, https://github.com/AllanChain/waka-jlab.git
Author-email: Allan Chain <allan-chain@outllok.com>
License: BSD 3-Clause License
License-File: LICENSE
Classifier: Framework :: Jupyter
Classifier: Framework :: Jupyter :: JupyterLab
Classifier: Framework :: Jupyter :: JupyterLab :: 4
Classifier: Framework :: Jupyter :: JupyterLab :: Extensions
Classifier: Framework :: Jupyter :: JupyterLab :: Extensions :: Prebuilt
Classifier: License :: OSI Approved :: BSD License
Classifier: Programming Language :: Python
Classifier: Programming Language :: Python :: 3
Classifier: Programming Language :: Python :: 3.8
Classifier: Programming Language :: Python :: 3.9
Classifier: Programming Language :: Python :: 3.10
Classifier: Programming Language :: Python :: 3.11
Classifier: Programming Language :: Python :: 3.12
Requires-Python: >=3.8
Requires-Dist: jupyter-server<3,>=2.0.1
